awspricing/__init__.py
awspricing/cache.py
awspricing/constants.py
awspricing/offers.py
awspricing-1.0.0.dist-info/DESCRIPTION.rst
awspricing-1.0.0.dist-info/METADATA
awspricing-1.0.0.dist-info/RECORD
awspricing-1.0.0.dist-info/WHEEL
awspricing-1.0.0.dist-info/metadata.json
awspricing-1.0.0.dist-info/top_level.txt
