Metadata-Version: 2.0
Name: awspricing
Version: 1.0.0
Summary: An SDK for AWS Pricing
Home-page: https://github.com/garrettheel/aws-pricing
Author: Garrett Heel
Author-email: UNKNOWN
License: apache2
Platform: UNKNOWN
Classifier: Development Status :: 5 - Production/Stable
Classifier: Intended Audience :: Developers
Classifier: Natural Language :: English
Classifier: License :: OSI Approved :: Apache Software License
Classifier: Programming Language :: Python
Classifier: Programming Language :: Python :: 2.7
Classifier: Programming Language :: Python :: 3
Classifier: Programming Language :: Python :: 3.3
Classifier: Programming Language :: Python :: 3.4
Classifier: Programming Language :: Python :: 3.5
Classifier: Programming Language :: Python :: 3.6
Requires-Dist: requests (<3.0.0,>=2.5.0)
Requires-Dist: six (<2.0.0,>=1.0.0)
Requires-Dist: typing (<3.6.0.0,>=3.5.0.0)
